{"id": 1032575490626908165, "user_id": 1486994990, "username": "delicatesoft", "timezone": "+03", "tweet": "Accounting Software in Dubai, UAE  https://youtu.be/kjIzeRZ74qk\u00a0 via @YouTube", "replies": 0, "retweets": 0, "likes": 0, "date": "2018-08-23", "time": "13:29:15", "hashtags": "", "mentions": "YouTube", "location": "", "link": "https://twitter.com/delicatesoft/status/1032575490626908165", "user_rt": "None"}
{"id": 1029039369187983360, "user_id": 1486994990, "username": "delicatesoft", "timezone": "+03", "tweet": "@issuu Profile of IT Company in Dubai UAE  https://issuu.com/delicatesoft/docs/delicate-software-solutions-profile?e=23651526/63793292\u00a0\u2026 via @Issuu", "replies": 0, "retweets": 0, "likes": 0, "date": "2018-08-13", "time": "19:17:58", "hashtags": "", "mentions": "issuu", "location": "", "link": "https://twitter.com/delicatesoft/status/1029039369187983360", "user_rt": "None"}
{"id": 1026787756184428546, "user_id": 1486994990, "username": "delicatesoft", "timezone": "+03", "tweet": "HR and Payroll Software by Delicate Software on #Google https://search.google.com/local/posts?q=HR+and+Payroll+Software+by+Delicate+Software&ludocid=2918232173653902155&lpsid=6870977653703130996\u00a0\u2026", "replies": 0, "retweets": 0, "likes": 0, "date": "2018-08-07", "time": "14:10:52", "hashtags": "#Google", "mentions": "", "location": "", "link": "https://twitter.com/delicatesoft/status/1026787756184428546", "user_rt": "None"}
{"id": 1019605243800227846, "user_id": 1486994990, "username": "delicatesoft", "timezone": "+03", "tweet": "phone installation in dubai uae  https://youtu.be/Ta9pn6h0FPU\u00a0 via @YouTube", "replies": 0, "retweets": 0, "likes": 0, "date": "2018-07-18", "time": "18:30:08", "hashtags": "", "mentions": "YouTube", "location": "", "link": "https://twitter.com/delicatesoft/status/1019605243800227846", "user_rt": "None"}
{"id": 1018167541443760130, "user_id": 1486994990, "username": "delicatesoft", "timezone": "+03", "tweet": "PABX AND TELEPHONE SYSTEMSINSTALLATION IN DUBAI, UAE https://www.linkedin.com/pulse/pabx-telephone-systems-installation-dubai-uae-balbir-singh/?published=t\u00a0\u2026", "replies": 0, "retweets": 0, "likes": 0, "date": "2018-07-14", "time": "19:17:13", "hashtags": "", "mentions": "", "location": "", "link": "https://twitter.com/delicatesoft/status/1018167541443760130", "user_rt": "None"}
{"id": 1018119818871033857, "user_id": 1486994990, "username": "delicatesoft", "timezone": "+03", "tweet": "Phone Pbx Installation Companies in Dubai to @delicatesoft #ReadMore  https://www.scribd.com/document/383836334/Telephone-Pbx-Installation-Companies-in-Dubai\u00a0\u2026", "replies": 0, "retweets": 0, "likes": 1, "date": "2018-07-14", "time": "16:07:35", "hashtags": "#ReadMore", "mentions": "delicatesoft", "location": "", "link": "https://twitter.com/delicatesoft/status/1018119818871033857", "user_rt": "None"}
