{"id": 1035157424892731392, "user_id": 225751736, "username": "noor_bank", "timezone": "+03", "tweet": "\u064a\u0645\u0643\u0646\u0643 \u0623\u0646 \u062a\u0643\u0648\u0646 \u0648\u0627\u062d\u062f\u064b\u0627 \u0645\u0646 \u0628\u064a\u0646 10 \u0641\u0627\u0626\u0632\u064a\u0646 \u0645\u062d\u0638\u0648\u0638\u064a\u0646 \u0628\u0647\u0627\u062a\u0641 iPhone X. \u0642\u0645 \u0628\u062a\u062d\u0648\u064a\u0644 2500 \u062f\u0631\u0647\u0645 \u062f\u0648\u0644\u064a\u064b\u0627 \u0628\u0639\u0645\u0644\u064a\u0629 \u062a\u062d\u0648\u064a\u0644 \u0648\u0627\u062d\u062f\u0629 \u0648\u0627\u062d\u0635\u0644 \u0639\u0644\u0649 \u0641\u0631\u0635\u0629 \u0627\u0644\u062f\u062e\u0648\u0644 \u0628\u0627\u0644\u0633\u062d\u0628. \u0636\u0627\u0639\u0641 \u0641\u0631\u0635\u0643 \u0628\u0627\u0644\u0631\u0628\u062d \u0643\u0644\u0645\u0627 \u0642\u0645\u062a \u0628\u0639\u0645\u0644\u064a\u0629 \u062a\u062d\u0648\u064a\u0644\u060c \u0644\u0644\u0642\u064a\u0627\u0645 \u0628\u0639\u0645\u0644\u064a\u0629 \u062a\u062d\u0648\u064a\u0644 \u0627\u0636\u063a\u0637 \u0647\u0646\u0627:  https://goo.gl/3GxXwg\u00a0\u064a\u0633\u0631\u064a \u0627\u0644\u0639\u0631\u0636 \u062d\u062a\u0649 \u062a\u0627\u0631\u064a\u062e 15 \u0623\u0643\u062a\u0648\u0628\u0631\u062a\u0637\u0628\u0642 \u0627\u0644\u0634\u0631\u0648\u0637 pic.twitter.com/vUf4Yn0gE0", "replies": 1, "retweets": 0, "likes": 1, "date": "2018-08-30", "time": "16:28:57", "hashtags": "", "mentions": "", "location": "", "link": "https://twitter.com/noor_bank/status/1035157424892731392", "user_rt": "None"}
{"id": 1035157173679079424, "user_id": 225751736, "username": "noor_bank", "timezone": "+03", "tweet": "You can be one of the 10 lucky winners to win an iPhone X this season. Transfer AED 2500 internationally in 1 transaction & get 1 entry in the draw. To transfer funds, click here:  https://goo.gl/3GxXwg\u00a0Offer valid up to 15th Oct on international fund transfers only. T&C apply. pic.twitter.com/CFsnTw4ddR", "replies": 0, "retweets": 0, "likes": 1, "date": "2018-08-30", "time": "16:27:57", "hashtags": "", "mentions": "", "location": "", "link": "https://twitter.com/noor_bank/status/1035157173679079424", "user_rt": "None"}
{"id": 1035097073731993600, "user_id": 225751736, "username": "noor_bank", "timezone": "+03", "tweet": "@Malakaf Thank you for sharing your contact details. Our team will contact you to assist you directly.", "replies": 0, "retweets": 0, "likes": 0, "date": "2018-08-30", "time": "12:29:08", "hashtags": "", "mentions": "Malakaf", "location": "", "link": "https://twitter.com/noor_bank/status/1035097073731993600", "user_rt": "None"}
{"id": 1035043975739174912, "user_id": 225751736, "username": "noor_bank", "timezone": "+03", "tweet": "@Malakaf Dear Malaka, please send us a DM with your mobile number and we will assist you directly.", "replies": 2, "retweets": 0, "likes": 0, "date": "2018-08-30", "time": "08:58:08", "hashtags": "", "mentions": "Malakaf", "location": "", "link": "https://twitter.com/noor_bank/status/1035043975739174912", "user_rt": "None"}
{"id": 1035043718515109889, "user_id": 225751736, "username": "noor_bank", "timezone": "+03", "tweet": "@mohannad_tweets Dear Mohannad, please send us a DM with your mobile number and we will assist you directly.", "replies": 0, "retweets": 0, "likes": 0, "date": "2018-08-30", "time": "08:57:07", "hashtags": "", "mentions": "mohannad_tweets", "location": "", "link": "https://twitter.com/noor_bank/status/1035043718515109889", "user_rt": "None"}
{"id": 1035043504639160320, "user_id": 225751736, "username": "noor_bank", "timezone": "+03", "tweet": "@sanjib_dreamer We trust this issue has been resolved to your satisfaction.  If you require any future support, be sure to let us know. We're here to help.", "replies": 0, "retweets": 0, "likes": 0, "date": "2018-08-30", "time": "08:56:16", "hashtags": "", "mentions": "sanjib_dreamer", "location": "", "link": "https://twitter.com/noor_bank/status/1035043504639160320", "user_rt": "None"}
{"id": 1034757267344814082, "user_id": 225751736, "username": "noor_bank", "timezone": "+03", "tweet": "@sanjib_dreamer Thank you for sharing your contact details. Our team will contact you to assist you directly.", "replies": 0, "retweets": 0, "likes": 0, "date": "2018-08-29", "time": "13:58:52", "hashtags": "", "mentions": "sanjib_dreamer", "location": "", "link": "https://twitter.com/noor_bank/status/1034757267344814082", "user_rt": "None"}
{"id": 1034688817754767360, "user_id": 225751736, "username": "noor_bank", "timezone": "+03", "tweet": "@sanjib_dreamer Please send us a DM with your mobile number and we will assist you directly.", "replies": 1, "retweets": 0, "likes": 0, "date": "2018-08-29", "time": "09:26:52", "hashtags": "", "mentions": "sanjib_dreamer", "location": "", "link": "https://twitter.com/noor_bank/status/1034688817754767360", "user_rt": "None"}
{"id": 1034328829832167425, "user_id": 225751736, "username": "noor_bank", "timezone": "+03", "tweet": "\u0646\u062d\u0646 \u0646\u062d\u062a\u0641\u0644 \u0627\u0644\u064a\u0648\u0645 \u0628\u0645\u0646\u0627\u0633\u0628\u0629 #\u064a\u0648\u0645_\u0627\u0644\u0645\u0631\u0623\u0629_\u0627\u0644\u0625\u0645\u0627\u0631\u0627\u062a\u064a\u0629! \u0648\u0642\u062f \u0642\u0627\u0645\u062a \u0645\u062c\u0645\u0648\u0639\u0629 \u0645\u0646 \u0627\u0644\u0625\u0645\u0627\u0631\u0627\u062a\u064a\u0627\u062a \u0628\u0627\u0644\u0645\u0634\u0627\u0631\u0643\u0629 \u0641\u064a \u0647\u0630\u0647 \u0627\u0644\u0645\u0628\u0627\u062f\u0631\u0629 \u062a\u0623\u0643\u064a\u062f\u0627\u064b \u0648\u062a\u0631\u0633\u064a\u062e\u0627\u064b \u0644\u0644\u0645\u0643\u0627\u0646\u0629 \u0627\u0644\u0645\u062a\u0645\u064a\u0632\u0629 \u0627\u0644\u062a\u064a \u062a\u062d\u0638\u0649 \u0628\u0647\u0627 \u0627\u0644\u0645\u0631\u0623\u0629 \u0641\u064a \u062f\u0648\u0644\u0629 \u0627\u0644\u0625\u0645\u0627\u0631\u0627\u062a. pic.twitter.com/WjpsMCOcCf", "replies": 0, "retweets": 1, "likes": 1, "date": "2018-08-28", "time": "09:36:24", "hashtags": "#\u064a\u0648\u0645_\u0627\u0644\u0645\u0631\u0623\u0629_\u0627\u0644\u0625\u0645\u0627\u0631\u0627\u062a\u064a\u0629", "mentions": "", "location": "", "link": "https://twitter.com/noor_bank/status/1034328829832167425", "user_rt": "None"}
{"id": 1034316226359689216, "user_id": 225751736, "username": "noor_bank", "timezone": "+03", "tweet": "We are celebrating Emirati Women\u2019s Day here at Noor Bank today! We asked some of our inspiring Emirati colleagues about the significance of the day and the role of Emirati women in the society and this is what they had to say.#EmiratiWomensDay #EmiratiWomen #WomensEmpowerment pic.twitter.com/xa81PgmrmY", "replies": 0, "retweets": 1, "likes": 1, "date": "2018-08-28", "time": "08:46:19", "hashtags": "#EmiratiWomensDay,#EmiratiWomen,#WomensEmpowerment", "mentions": "", "location": "", "link": "https://twitter.com/noor_bank/status/1034316226359689216", "user_rt": "None"}
{"id": 1034026279522185216, "user_id": 225751736, "username": "noor_bank", "timezone": "+03", "tweet": "@faisalin1 Please send us a DM with your mobile number and we will assist you directly.", "replies": 0, "retweets": 0, "likes": 0, "date": "2018-08-27", "time": "13:34:10", "hashtags": "", "mentions": "faisalin1", "location": "", "link": "https://twitter.com/noor_bank/status/1034026279522185216", "user_rt": "None"}
{"id": 1033947558828273669, "user_id": 225751736, "username": "noor_bank", "timezone": "+03", "tweet": "@faisalin1 Thank you for reaching out to Noor, please call our 24-hour contact centre on 800 6667 within the UAE or 009714-4274343 from outside the UAE and our team will assist you.", "replies": 1, "retweets": 0, "likes": 0, "date": "2018-08-27", "time": "08:21:22", "hashtags": "", "mentions": "faisalin1", "location": "", "link": "https://twitter.com/noor_bank/status/1033947558828273669", "user_rt": "None"}
{"id": 1033715514848235520, "user_id": 225751736, "username": "noor_bank", "timezone": "+03", "tweet": "@bree_khan We are sorry to hear this and would like to help. Please send us a DM with your mobile number and we will assist you directly.", "replies": 1, "retweets": 0, "likes": 0, "date": "2018-08-26", "time": "16:59:18", "hashtags": "", "mentions": "bree_khan", "location": "", "link": "https://twitter.com/noor_bank/status/1033715514848235520", "user_rt": "None"}
{"id": 1033668187466989568, "user_id": 225751736, "username": "noor_bank", "timezone": "+03", "tweet": "\u062a\u062a\u064a\u062d \u0644\u0643 \u0628\u0637\u0627\u0642\u0627\u062a\u0646\u0627 \u0627\u0644\u062c\u062f\u064a\u062f\u0629 \u0641\u0631\u0635\u0629 \u0644\u0631\u062f \u0627\u0644\u062c\u0645\u064a\u0644 \u0645\u0646 \u062e\u0644\u0627\u0644 \u0634\u0631\u0627\u0643\u062a\u0646\u0627 \u0645\u0639 \u0645\u0624\u0633\u0633\u0629 \u0645\u0648\u0627\u0647\u0628 \u0641\u0631\u0648\u0645 \u0628\u064a\u0648\u062a\u064a\u0641\u0648\u0644 \u0628\u064a\u0628\u0648\u0644 \u0627\u0644\u062a\u064a \u062a\u062f\u0639\u0645 \u0645\u0634\u0627\u0631\u0643\u0629 \u0623\u0635\u062d\u0627\u0628 \u0627\u0644\u0647\u0645\u0645 \u0648\u0625\u0628\u0631\u0627\u0632 \u0642\u062f\u0631\u0627\u062a\u0647\u0645 \u0627\u0644\u0644\u0627\u0645\u062d\u062f\u0648\u062f\u0629. \u062a\u0645 \u062a\u0635\u0645\u064a\u0645 \u0635\u0646\u0627\u062f\u064a\u0642 \u0627\u0644\u062a\u0631\u062d\u064a\u0628 \u0627\u0644\u062e\u0627\u0635\u0629 \u0628\u0639\u0645\u0644\u0627\u0626\u0646\u0627 \u0645\u0646 \u0642\u0628\u0644 \u0645\u062e\u062a\u0644\u0641 \u0627\u0644\u0641\u0646\u0627\u0646\u064a\u0646 \u0641\u064a \u0645\u0624\u0633\u0633\u0629 \u0645\u0648\u0627\u0647\u0628. @mawahebdubai#\u0623\u0635\u062d\u0627\u0628_\u0627\u0644\u0647\u0645\u0645 #\u0646\u0648\u0631_\u0628\u0646\u0643 pic.twitter.com/ln13Z5bM35", "replies": 0, "retweets": 0, "likes": 1, "date": "2018-08-26", "time": "13:51:15", "hashtags": "#\u0623\u0635\u062d\u0627\u0628_\u0627\u0644\u0647\u0645\u0645,#\u0646\u0648\u0631_\u0628\u0646\u0643", "mentions": "mawahebdubai", "location": "", "link": "https://twitter.com/noor_bank/status/1033668187466989568", "user_rt": "None"}
{"id": 1033628585444171776, "user_id": 225751736, "username": "noor_bank", "timezone": "+03", "tweet": "Our cards offer you the chance to give back through a special partnership with Mawaheb from Beautiful People\u2013 an art studio that empowers \u2018The Determined Ones\u2019. The unique art on our welcome boxes is created by various Mawaheb artists. @mawahebdubai#Mawaheb #TheDeterminedOnes pic.twitter.com/4fvUC1Y79J", "replies": 0, "retweets": 2, "likes": 4, "date": "2018-08-26", "time": "11:13:53", "hashtags": "#Mawaheb,#TheDeterminedOnes", "mentions": "mawahebdubai", "location": "", "link": "https://twitter.com/noor_bank/status/1033628585444171776", "user_rt": "None"}
{"id": 1033312801572507648, "user_id": 225751736, "username": "noor_bank", "timezone": "+03", "tweet": "\u0627\u0646\u0637\u0644\u0642 \u0645\u0646 0\u066a \u0625\u0644\u0649 100\u066a \u0641\u064a 60 \u062f\u0642\u064a\u0642\u0629!\u0627\u062d\u0635\u0644 \u0639\u0644\u0649 \u0633\u064a\u0627\u0631\u0629 \u0623\u062d\u0644\u0627\u0645\u0643 \u0645\u0639 \u0645\u0648\u0627\u0641\u0642\u0629 \u0645\u0628\u062f\u0626\u064a\u0629 \u0645\u0646 \u0646\u0648\u0631 \u0628\u0646\u0643 \u062e\u0644\u0627\u0644 60 \u062f\u0642\u064a\u0642\u0629 \u0641\u0642\u0637 \u0648\u0645\u0639\u062f\u0644\u0627\u062a \u0631\u0628\u062d \u0644\u0644\u0633\u064a\u0627\u0631\u0627\u062a \u0627\u0644\u0645\u0633\u062a\u0639\u0645\u0644\u0629 \u0645\u0646 2.99\u066a.\u0647\u0630\u0627 \u0627\u0644\u0639\u0631\u0636 \u0633\u0627\u0631\u064a \u0644\u0641\u062a\u0631\u0629 \u0645\u062d\u062f\u0648\u062f\u0629 \u0648 \u062e\u0627\u0635 \u0628\u062a\u0645\u0648\u064a\u0644 \u0634\u0631\u0627\u0621 \u0627\u0644\u0633\u064a\u0627\u0631\u0627\u062a \u0627\u0644\u0645\u0633\u062a\u0639\u0645\u0644\u0629 \u0641\u0642\u0637 \u062a\u0642\u062f\u0645 \u0628\u0637\u0644\u0628\u0643 \u0627\u0644\u064a\u0648\u0645!\u062a\u0637\u0628\u0642 \u0627\u0644\u0634\u0631\u0648\u0637 \u0648\u0627\u0644\u0623\u062d\u0643\u0627\u0645 pic.twitter.com/IJKjkg5wYK", "replies": 0, "retweets": 0, "likes": 2, "date": "2018-08-25", "time": "14:19:04", "hashtags": "", "mentions": "", "location": "", "link": "https://twitter.com/noor_bank/status/1033312801572507648", "user_rt": "None"}
{"id": 1033312487490375681, "user_id": 225751736, "username": "noor_bank", "timezone": "+03", "tweet": "From 0% to 100% in 60 minutes!Get the car of your dreams with a pre-approval from Noor Bank in 60 minutes. Profit rates starting from 2.99% for pre-owned cars. Terms & Conditions apply. This is a limited time offer & valid for pre-owned cars only. Apply now!#AutoFinance pic.twitter.com/iFdOP5ygyA", "replies": 0, "retweets": 0, "likes": 2, "date": "2018-08-25", "time": "14:17:49", "hashtags": "#AutoFinance", "mentions": "", "location": "", "link": "https://twitter.com/noor_bank/status/1033312487490375681", "user_rt": "None"}
{"id": 1033268682204635141, "user_id": 225751736, "username": "noor_bank", "timezone": "+03", "tweet": "@nnejoumi We are sorry to hear this and would like to help. Please send us a DM with your mobile number and we will assist you directly.", "replies": 0, "retweets": 0, "likes": 0, "date": "2018-08-25", "time": "11:23:45", "hashtags": "", "mentions": "nnejoumi", "location": "", "link": "https://twitter.com/noor_bank/status/1033268682204635141", "user_rt": "None"}
{"id": 1033267884900970497, "user_id": 225751736, "username": "noor_bank", "timezone": "+03", "tweet": "@mo91658172 We are sorry to hear this, our team will be in contact with you shortly to assist you directly.", "replies": 0, "retweets": 0, "likes": 0, "date": "2018-08-25", "time": "11:20:35", "hashtags": "", "mentions": "mo91658172", "location": "", "link": "https://twitter.com/noor_bank/status/1033267884900970497", "user_rt": "None"}
{"id": 1032609124750708739, "user_id": 225751736, "username": "noor_bank", "timezone": "+03", "tweet": "10\u0645\u0644\u0627\u064a\u064a\u0646 \u0646\u0642\u0637\u0629 \u0645\u0643\u0627\u0641\u0623\u0629 \u0644\u0644\u0627\u062d\u062a\u0641\u0627\u0644 \u0647\u0630\u0627 \u0627\u0644\u0635\u064a\u0641! \u0647\u0644 \u062a\u0631\u063a\u0628 \u0623\u0646 \u062a\u0643\u0648\u0646 \u0636\u0645\u0646 \u0627\u0644\u0639\u062f\u064a\u062f \u0645\u0646 \u0627\u0644\u0641\u0627\u0626\u0632\u064a\u0646 \u0627\u0644\u0645\u062d\u0638\u0648\u0638\u064a\u0646\u061f \u0634\u0627\u0647\u062f \u0647\u0630\u0627 \u0627\u0644\u0641\u064a\u062f\u064a\u0648 \u0644\u0645\u0639\u0631\u0641\u0629 \u0643\u064a\u0641 \u064a\u0645\u0643\u0646\u0643 \u0630\u0644\u0643! \u0636\u0627\u0639\u0641 \u0641\u0631\u0635\u0643 \u0641\u064a \u0627\u0644\u0641\u0648\u0632 \u0639\u0646\u062f \u0625\u0646\u0641\u0627\u0642\u0643 \u0645\u0628\u0627\u0644\u063a \u0623\u0643\u062b\u0631.#10_\u0645\u0644\u064a\u0648\u0646 #\u0645\u0643\u0627\u0641\u0623\u0629 #\u0625\u0631\u0628\u062d_\u0645\u0639_\u0646\u0648\u0631_\u0628\u0646\u0643 #\u0646\u0648\u0631_\u0628\u0646\u0643 #\u0627\u0644\u062e\u062f\u0645\u0627\u062a_\u0627\u0644\u0645\u0635\u0631\u0641\u064a\u0629 pic.twitter.com/X4mFyam3Y1", "replies": 0, "retweets": 0, "likes": 2, "date": "2018-08-23", "time": "15:42:54", "hashtags": "#10_\u0645\u0644\u064a\u0648\u0646,#\u0645\u0643\u0627\u0641\u0623\u0629,#\u0625\u0631\u0628\u062d_\u0645\u0639_\u0646\u0648\u0631_\u0628\u0646\u0643,#\u0646\u0648\u0631_\u0628\u0646\u0643,#\u0627\u0644\u062e\u062f\u0645\u0627\u062a_\u0627\u0644\u0645\u0635\u0631\u0641\u064a\u0629", "mentions": "", "location": "", "link": "https://twitter.com/noor_bank/status/1032609124750708739", "user_rt": "None"}
{"id": 1032608757191245829, "user_id": 225751736, "username": "noor_bank", "timezone": "+03", "tweet": "This summer, we are giving away 10 million reward points! Entering the draw is easy & the more you spend the more you increase your chances of winning. Watch this video to learn how you could be one of the many lucky winners!#10Million #RewardPoints #WinWithNoorBank #NoorBank pic.twitter.com/pFp9VQCkV3", "replies": 1, "retweets": 0, "likes": 1, "date": "2018-08-23", "time": "15:41:27", "hashtags": "#10Million,#RewardPoints,#WinWithNoorBank,#NoorBank", "mentions": "", "location": "", "link": "https://twitter.com/noor_bank/status/1032608757191245829", "user_rt": "None"}
{"id": 1032226756105777152, "user_id": 225751736, "username": "noor_bank", "timezone": "+03", "tweet": "\u0646\u062d\u0646 \u0639\u0644\u0649 \u0623\u0628\u0648\u0627\u0628 \u0627\u0644\u0639\u0648\u062f\u0629 \u0625\u0644\u0649 \u0627\u0644\u0645\u062f\u0631\u0633\u0629\u060c \u0623\u0646\u0641\u0642 500 \u062f\u0631\u0647\u0645 \u0623\u0648 \u0623\u0643\u062b\u0631 \u0639\u0644\u0649 \u0628\u0637\u0627\u0642\u0629 \u0627\u0644\u062e\u0635\u0645 \u0623\u0648 \u0627\u0644\u0627\u0626\u062a\u0645\u0627\u0646 \u0645\u0646 \u0646\u0648\u0631 \u0628\u0646\u0643 \u0648\u0627\u062d\u0635\u0644 \u0639\u0644\u0649 \u0641\u0631\u0635\u0629 \u0644\u0644\u0641\u0648\u0632 \u0628\u0645\u0628\u0644\u063a \u064a\u0635\u0644 \u0625\u0644\u0649 10,000 \u062f\u0631\u0647\u0645 \u0634\u0647\u0631\u064a\u0627\u064b.\u064a\u0646\u062a\u0647\u064a \u0627\u0644\u0639\u0631\u0636 \u0641\u064a 14 \u0633\u0628\u062a\u0645\u0628\u0631.\u062a\u0637\u0628\u0642 \u0627\u0644\u0634\u0631\u0648\u0637 \u0648\u0627\u0644\u0623\u062d\u0643\u0627\u0645. pic.twitter.com/brcArMdWUo", "replies": 1, "retweets": 0, "likes": 2, "date": "2018-08-22", "time": "14:23:31", "hashtags": "", "mentions": "", "location": "", "link": "https://twitter.com/noor_bank/status/1032226756105777152", "user_rt": "None"}
{"id": 1032217177884110850, "user_id": 225751736, "username": "noor_bank", "timezone": "+03", "tweet": "This back to school season, spend AED 500 or more on your debit card and get a chance to win up to AED 10,000 every month. Offer ends 14 Sep'18. Visit:  https://goo.gl/6XAJAc\u00a0Terms & conditions apply.#BackToSchool #NoorBank #Banking #UAEBanking pic.twitter.com/pqIbalwuu5", "replies": 0, "retweets": 0, "likes": 1, "date": "2018-08-22", "time": "13:45:27", "hashtags": "#BackToSchool,#NoorBank,#Banking,#UAEBanking", "mentions": "", "location": "", "link": "https://twitter.com/noor_bank/status/1032217177884110850", "user_rt": "None"}
{"id": 1031832649030090754, "user_id": 225751736, "username": "noor_bank", "timezone": "+03", "tweet": "\u0627\u0644\u0622\u0646 \u0645\u0639 \u0646\u0648\u0631 \u0628\u0646\u0643\u060c \u0627\u0633\u062a\u0631\u062f \u0646\u0642\u0648\u062f\u0643 \u0628\u064a\u0646\u0645\u0627 \u062a\u0633\u062a\u0645\u062a\u0639 \u0628\u0627\u0644\u062a\u0648\u0627\u0635\u0644 \u0645\u0639 \u0627\u0644\u0623\u0635\u062f\u0642\u0627\u0621 \u0648\u0627\u0644\u0639\u0627\u0626\u0644\u0629 \u0641\u064a \u062c\u0645\u064a\u0639 \u0623\u0646\u062d\u0627\u0621 \u0627\u0644\u0639\u0627\u0644\u0645 \u0645\u0646 \u062e\u0644\u0627\u0644 BOTIM \u0623\u0648 C'me!\u0639\u0631\u0636 \u062d\u0635\u0631\u064a \u0644\u062d\u0627\u0645\u0644\u064a \u0628\u0637\u0627\u0642\u0629 \u0627\u0626\u062a\u0645\u0627\u0646 \u0646\u0648\u0631 \u0628\u0646\u0643.\u0644\u0645\u0639\u0631\u0641\u0629 \u0627\u0644\u0645\u0632\u064a\u062f:   https://goo.gl/pc2GsK\u00a0#\u0646\u0648\u0631_\u0628\u0646\u0643 #\u0627\u0644\u062e\u062f\u0645\u0627\u062a_\u0627\u0644\u0645\u0635\u0631\u0641\u064a\u0629 #\u0645\u0643\u0627\u0644\u0645\u0627\u062a_\u062f\u0648\u0644\u064a\u0629 pic.twitter.com/CqJNFvoQZN", "replies": 0, "retweets": 0, "likes": 1, "date": "2018-08-21", "time": "12:17:28", "hashtags": "#\u0646\u0648\u0631_\u0628\u0646\u0643,#\u0627\u0644\u062e\u062f\u0645\u0627\u062a_\u0627\u0644\u0645\u0635\u0631\u0641\u064a\u0629,#\u0645\u0643\u0627\u0644\u0645\u0627\u062a_\u062f\u0648\u0644\u064a\u0629", "mentions": "", "location": "", "link": "https://twitter.com/noor_bank/status/1031832649030090754", "user_rt": "None"}
{"id": 1031832526397079552, "user_id": 225751736, "username": "noor_bank", "timezone": "+03", "tweet": "Now with Noor Bank get cashback while you enjoy endless conversations with friends & family across the globe through BOTIM or C\u2019me! Exclusive offer for Noor Bank credit card holders only. Click to learn more:  https://goo.gl/pc2GsK\u00a0#NoorBank #UAEBanking #Banking #CallingPlan pic.twitter.com/oz8qC24CRs", "replies": 0, "retweets": 0, "likes": 1, "date": "2018-08-21", "time": "12:16:59", "hashtags": "#NoorBank,#UAEBanking,#Banking,#CallingPlan", "mentions": "", "location": "", "link": "https://twitter.com/noor_bank/status/1031832526397079552", "user_rt": "None"}
{"id": 1031472280612864001, "user_id": 225751736, "username": "noor_bank", "timezone": "+03", "tweet": "\u064a\u0643\u0627\u0641\u0626\u0643 \u0628\u0631\u0646\u0627\u0645\u062c Link  \u0641\u064a \u0643\u0644 \u0645\u0631\u0629 \u062a\u062a\u0639\u0627\u0645\u0644 \u0641\u064a\u0647\u0627 \u0645\u0639\u0646\u0627.\u064a\u0633\u0627\u0639\u062f\u0643 \u0645\u062a\u0648\u0633\u0637 \u0627\u0644\u0631\u0635\u064a\u062f \u0627\u0644\u0634\u0647\u0631\u064a \u0648\u0627\u0644\u0645\u0639\u0627\u0645\u0644\u0627\u062a \u0627\u0644\u0645\u0635\u0631\u0641\u064a\u0629 \u0639\u0628\u0631 \u0627\u0644\u0625\u0646\u062a\u0631\u0646\u062a \u0648\u0627\u0644\u0645\u0646\u062a\u062c\u0627\u062a \u0627\u0644\u062c\u062f\u064a\u062f\u0629 \u0639\u0644\u0649 \u062c\u0645\u0639 \u0646\u0642\u0627\u0637 \u0627\u0644\u0645\u0643\u0627\u0641\u0622\u062a \u0648\u0627\u0644\u062d\u0635\u0648\u0644 \u0639\u0644\u0649 \u0627\u0644\u0645\u0632\u064a\u062f \u0645\u0646 \u062e\u064a\u0627\u0631\u0627\u062a \u0627\u0644\u0627\u0633\u062a\u0631\u062f\u0627\u062f.\u062d\u0645\u0644 \u0627\u0644\u062a\u0637\u0628\u064a\u0642 \u0627\u0644\u0622\u0646: \u0645\u062a\u062c\u0631 \u062c\u0648\u062c\u0644:  https://goo.gl/xZuxQR\u00a0  \u0645\u062a\u062c\u0631 \u0622\u0628\u0644:  https://goo.gl/jQKqkS\u00a0 pic.twitter.com/iMlrCQhuKx", "replies": 0, "retweets": 0, "likes": 2, "date": "2018-08-20", "time": "12:25:30", "hashtags": "", "mentions": "", "location": "", "link": "https://twitter.com/noor_bank/status/1031472280612864001", "user_rt": "None"}
{"id": 1031472203253067777, "user_id": 225751736, "username": "noor_bank", "timezone": "+03", "tweet": "Our Link Rewards account rewards you every time you bank with us.Monthly Average Balance, online banking transactions and new products will help you collect reward points and get  you more redemption optionsGoogle Play: https://goo.gl/xZuxQR\u00a0      Apple: https://goo.gl/jQKqkS\u00a0 pic.twitter.com/mYNlIgyqf5", "replies": 0, "retweets": 0, "likes": 2, "date": "2018-08-20", "time": "12:25:11", "hashtags": "", "mentions": "", "location": "", "link": "https://twitter.com/noor_bank/status/1031472203253067777", "user_rt": "None"}
{"id": 1031462925146497024, "user_id": 225751736, "username": "noor_bank", "timezone": "+03", "tweet": "5 \u062f\u0642\u0627\u0626\u0642 \u0647\u064a \u0643\u0644 \u0645\u0627 \u062a\u062d\u062a\u0627\u062c\u0647 \u0644\u062a\u0623\u0645\u064a\u0646 \u0627\u062d\u062a\u064a\u0627\u062c\u0627\u062a\u0643 \u0627\u0644\u0645\u0627\u0644\u064a\u0629 \u0645\u0639 \u0646\u0648\u0631 \u0628\u0646\u0643\u060c \u062a\u0642\u062f\u0645 \u0628\u0637\u0644\u0628\u0643 \u0639\u0628\u0631 \u0645\u0648\u0642\u0639\u0646\u0627 \u0627\u0644\u0627\u0644\u0643\u062a\u0631\u0648\u0646\u064a \u0648\u0627\u062d\u0635\u0644 \u0639\u0644\u0649 \u0645\u0648\u0627\u0641\u0642\u0629 \u0645\u0633\u0628\u0642\u0629.\u0627\u062d\u0635\u0644 \u0639\u0644\u0649 \u0642\u0633\u064a\u0645\u0629 \u0633\u0641\u0631 \u0645\u0646 Holiday Factory \u0628\u0642\u064a\u0645\u0629 500 \u062f\u0631\u0647\u0645 \u0644\u0643\u0644 \u0637\u0644\u0628 \u0646\u0627\u062c\u062d! \u0627\u0644\u0639\u0631\u0636 \u0635\u0627\u0644\u062d \u0644\u0644\u0628\u0637\u0627\u0642\u0627\u062a \u0627\u0644\u0627\u0626\u062a\u0645\u0627\u0646\u064a\u0629 \u0648\u0627\u0644\u062a\u0645\u0648\u064a\u0644 \u0627\u0644\u0634\u062e\u0635\u064a \u0648\u062a\u0645\u0648\u064a\u0644 \u0627\u0644\u0633\u064a\u0627\u0631\u0627\u062a. pic.twitter.com/I8uJJ6HyOf", "replies": 0, "retweets": 0, "likes": 4, "date": "2018-08-20", "time": "11:48:19", "hashtags": "", "mentions": "", "location": "", "link": "https://twitter.com/noor_bank/status/1031462925146497024", "user_rt": "None"}
{"id": 1031460857883049984, "user_id": 225751736, "username": "noor_bank", "timezone": "+03", "tweet": "5 minutes is all it takes to secure your financial freedom with Noor Bank. Apply online at  http://www.noorbank.com\u00a0 in less than 5 minutes & get a pre-approval for your financial needs..Apply today & get a 500 AED Holiday Factory travel voucher for every successful application! pic.twitter.com/A8Xdw7zR2n", "replies": 0, "retweets": 0, "likes": 2, "date": "2018-08-20", "time": "11:40:06", "hashtags": "", "mentions": "", "location": "", "link": "https://twitter.com/noor_bank/status/1031460857883049984", "user_rt": "None"}
{"id": 1031160521427505152, "user_id": 225751736, "username": "noor_bank", "timezone": "+03", "tweet": "\u062a\u0647\u0627\u0646\u064a\u0646\u0627 \u0644\u062c\u0645\u064a\u0639 \u0627\u0644\u0641\u0627\u0626\u0632\u064a\u0646 \u0628\u0640 10 \u0645\u0644\u0627\u064a\u064a\u0646 \u0646\u0642\u0637\u0629 \u0645\u0643\u0627\u0641\u0623\u0629! \u062a\u0631\u0642\u0628\u0648\u0627 \u0627\u0644\u0645\u0632\u064a\u062f \u0648\u0642\u062f \u062a\u0643\u0648\u0646 \u0623\u0646\u062a \u0627\u0644\u0631\u0627\u0628\u062d \u0627\u0644\u062a\u0627\u0644\u064a!#10_\u0645\u0644\u064a\u0648\u0646 #\u0645\u0643\u0627\u0641\u0623\u0629 #\u0625\u0631\u0628\u062d_\u0645\u0639_\u0646\u0648\u0631_\u0628\u0646\u0643 #\u0646\u0648\u0631_\u0628\u0646\u0643 #\u0627\u0644\u062e\u062f\u0645\u0627\u062a_\u0627\u0644\u0645\u0635\u0631\u0641\u064a\u0629 pic.twitter.com/0Lnlm3uOBz", "replies": 0, "retweets": 0, "likes": 3, "date": "2018-08-19", "time": "15:46:41", "hashtags": "#10_\u0645\u0644\u064a\u0648\u0646,#\u0645\u0643\u0627\u0641\u0623\u0629,#\u0625\u0631\u0628\u062d_\u0645\u0639_\u0646\u0648\u0631_\u0628\u0646\u0643,#\u0646\u0648\u0631_\u0628\u0646\u0643,#\u0627\u0644\u062e\u062f\u0645\u0627\u062a_\u0627\u0644\u0645\u0635\u0631\u0641\u064a\u0629", "mentions": "", "location": "", "link": "https://twitter.com/noor_bank/status/1031160521427505152", "user_rt": "None"}
{"id": 1031158808373075968, "user_id": 225751736, "username": "noor_bank", "timezone": "+03", "tweet": "Congratulations to all the winners of our 10 Million Reward Points Bonanza! Stay tuned for more updates on how you can be the next lucky winner!#10Million #RewardPoints #WinWithNoorBank #NoorBank #UAEBanking #Banking pic.twitter.com/2pJ6qMEyIN", "replies": 1, "retweets": 0, "likes": 2, "date": "2018-08-19", "time": "15:39:52", "hashtags": "#10Million,#RewardPoints,#WinWithNoorBank,#NoorBank,#UAEBanking,#Banking", "mentions": "", "location": "", "link": "https://twitter.com/noor_bank/status/1031158808373075968", "user_rt": "None"}
{"id": 1031122068262330369, "user_id": 225751736, "username": "noor_bank", "timezone": "+03", "tweet": "\u0646\u062a\u0645\u0646\u0649 \u0644\u0643 \u0648\u0644\u0639\u0627\u0626\u0644\u062a\u0643 \u0639\u064a\u062f\u0627\u064b \u0645\u0628\u0627\u0631\u0643\u0627\u064b \u0648\u0633\u0639\u064a\u062f\u0627\u064bWe wish you and your family a blessed Eid Al-Adha pic.twitter.com/6PS1pg5837", "replies": 0, "retweets": 1, "likes": 3, "date": "2018-08-19", "time": "13:13:53", "hashtags": "", "mentions": "", "location": "", "link": "https://twitter.com/noor_bank/status/1031122068262330369", "user_rt": "None"}
{"id": 1031064601482457090, "user_id": 225751736, "username": "noor_bank", "timezone": "+03", "tweet": "@ManalAlboloshi @amna_banna Thank you so much for sharing this positive feedback with us. You have made our day!", "replies": 1, "retweets": 0, "likes": 1, "date": "2018-08-19", "time": "09:25:31", "hashtags": "", "mentions": "amna_banna,ManalAlboloshi", "location": "", "link": "https://twitter.com/noor_bank/status/1031064601482457090", "user_rt": "None"}
{"id": 1031064060652134400, "user_id": 225751736, "username": "noor_bank", "timezone": "+03", "tweet": "@mo91658172 We are sorry to hear this, our team will be in contact with you shortly to assist you directly.", "replies": 0, "retweets": 0, "likes": 0, "date": "2018-08-19", "time": "09:23:22", "hashtags": "", "mentions": "mo91658172", "location": "", "link": "https://twitter.com/noor_bank/status/1031064060652134400", "user_rt": "None"}
{"id": 1031064025751273472, "user_id": 225751736, "username": "noor_bank", "timezone": "+03", "tweet": "@mo91658172 We are sorry to hear this, our team will be in contact with you shortly to assist you directly.", "replies": 0, "retweets": 0, "likes": 0, "date": "2018-08-19", "time": "09:23:14", "hashtags": "", "mentions": "mo91658172", "location": "", "link": "https://twitter.com/noor_bank/status/1031064025751273472", "user_rt": "None"}
{"id": 1030081225170608128, "user_id": 225751736, "username": "noor_bank", "timezone": "+03", "tweet": "@mo91658172 Please send us a DM with your mobile number and we will arrange to call you back straightaway, or contact us at 800 6667.", "replies": 1, "retweets": 0, "likes": 0, "date": "2018-08-16", "time": "16:17:56", "hashtags": "", "mentions": "mo91658172", "location": "", "link": "https://twitter.com/noor_bank/status/1030081225170608128", "user_rt": "None"}
{"id": 1030081190819184640, "user_id": 225751736, "username": "noor_bank", "timezone": "+03", "tweet": "@mo91658172 Please send us a DM with your mobile number and we will arrange to call you back straightaway, or contact us at 800 6667.", "replies": 1, "retweets": 0, "likes": 0, "date": "2018-08-16", "time": "16:17:48", "hashtags": "", "mentions": "mo91658172", "location": "", "link": "https://twitter.com/noor_bank/status/1030081190819184640", "user_rt": "None"}
{"id": 1030076739169464321, "user_id": 225751736, "username": "noor_bank", "timezone": "+03", "tweet": "\u0631\u062d\u0628\u0648 \u0628\u0627\u0644\u062a\u062c\u0631\u0628\u0629 \u0627\u0644\u0645\u0635\u0631\u0641\u064a\u0629 \u0627\u0644\u0645\u062a\u0645\u064a\u0632\u0629 \u0645\u0646 \u062e\u0644\u0627\u0644 \u0627\u0644\u0645\u0646\u0635\u0629 \u0627\u0644\u0630\u0643\u064a\u0629 \u0644\u0644\u062e\u062f\u0645\u0627\u062a \u0627\u0644\u0645\u0635\u0631\u0641\u064a\u0629 \u0627\u0644\u062a\u064a \u062a\u0645 \u0625\u0637\u0644\u0627\u0642\u0647\u0627 \u0645\u0624\u062e\u0631\u064b\u0627 \u0645\u0646 \u0623\u062c\u0644\u0643\u0645 \u0644\u062a\u0643\u0648\u0646 \u0623\u0643\u062b\u0631 \u0633\u0644\u0627\u0633\u0629 \u0648\u0633\u0631\u0639\u0629\u060c \u062d\u064a\u062b \u0627\u0631\u062a\u0642\u064a\u0646\u0627 \u0628\u0627\u0644\u0639\u0645\u0644\u064a\u0627\u062a \u0627\u0644\u0645\u0635\u0631\u0641\u064a\u0629 \u0625\u0644\u0649 \u0622\u0641\u0627\u0642 \u062c\u062f\u064a\u062f\u0629.  https://digital.noorbank.com/PersonalBanking\u00a0 /#\u0646\u0648\u0631_\u0628\u0646\u0643 #\u0627\u0644\u0625\u0645\u0627\u0631\u0627\u062a #\u0627\u0644\u0623\u0639\u0645\u0627\u0644_\u0627\u0644\u0645\u0635\u0631\u0641\u064a\u0629 pic.twitter.com/iWQ0LBEIYW", "replies": 2, "retweets": 2, "likes": 3, "date": "2018-08-16", "time": "16:00:07", "hashtags": "#\u0646\u0648\u0631_\u0628\u0646\u0643,#\u0627\u0644\u0625\u0645\u0627\u0631\u0627\u062a,#\u0627\u0644\u0623\u0639\u0645\u0627\u0644_\u0627\u0644\u0645\u0635\u0631\u0641\u064a\u0629", "mentions": "", "location": "", "link": "https://twitter.com/noor_bank/status/1030076739169464321", "user_rt": "None"}
{"id": 1030076189359136768, "user_id": 225751736, "username": "noor_bank", "timezone": "+03", "tweet": "Say hello to a refreshed banking experience with our newly launched Internet Banking platform for our retail customers. With a smoother and faster interface, banking will never be the same.  https://digital.noorbank.com/PersonalBanking/\u00a0\u2026#InternetBanking #NoorBank #UAEBanking #Banking #Dubai #MyDubai pic.twitter.com/EeZ9vmMfdi", "replies": 0, "retweets": 1, "likes": 5, "date": "2018-08-16", "time": "15:57:56", "hashtags": "#InternetBanking,#NoorBank,#UAEBanking,#Banking,#Dubai,#MyDubai", "mentions": "", "location": "", "link": "https://twitter.com/noor_bank/status/1030076189359136768", "user_rt": "None"}
{"id": 1029718455568740352, "user_id": 225751736, "username": "noor_bank", "timezone": "+03", "tweet": "\u062c\u0647\u0632\u0646\u0627 \u0644\u0643 \u0623\u0641\u0636\u0644 \u0647\u062f\u064a\u0629 \u0644\u062a\u0647\u062f\u064a\u0647\u0627 \u0644\u0623\u062d\u0628\u0627\u0626\u0643 \u0641\u064a \u0639\u064a\u062f \u0627\u0644\u0623\u0636\u062d\u0649 \u0627\u0644\u0645\u0628\u0627\u0631\u0643 \u0645\u0646 \u062e\u0644\u0627\u0644 \u0628\u0637\u0627\u0642\u0627\u062a eGift \u0648\u0627\u0644\u062a\u064a \u062a\u0634\u0645\u0644 \u0623\u0634\u0647\u0631 \u0627\u0644\u0639\u0644\u0627\u0645\u0627\u062a \u0627\u0644\u062a\u062c\u0627\u0631\u064a\u0629 \u0627\u0644\u0645\u0641\u0636\u0644\u0629 \u0644\u062f\u064a\u0647\u0645!\u0627\u0633\u062a\u0645\u062a\u0639 \u0628\u062e\u0635\u0648\u0645\u0627\u062a \u062e\u0627\u0635\u0629 \u0639\u0646\u062f \u0627\u0633\u062a\u062e\u062f\u0627\u0645\u0643 \u0628\u0637\u0627\u0642\u0627\u062a \u0627\u0644\u062e\u0635\u0645 \u0623\u0648 \u0627\u0644\u0627\u0626\u062a\u0645\u0627\u0646 \u0645\u0646 \u0646\u0648\u0631 \u0628\u0646\u0643  \u0639\u0646\u062f \u0627\u0644\u062f\u0641\u0639. \u0627\u0644\u0639\u0631\u0636 \u0633\u0627\u0631\u064a \u0645\u0646 14 \u0625\u0644\u0649 31 \u0623\u063a\u0633\u0637\u0633.\u0644\u0644\u0645\u0632\u064a\u062f:  https://yougotagift.com/offers/noorbank/\u00a0\u2026 pic.twitter.com/5UIdmacMDi", "replies": 1, "retweets": 1, "likes": 3, "date": "2018-08-15", "time": "16:16:25", "hashtags": "", "mentions": "", "location": "", "link": "https://twitter.com/noor_bank/status/1029718455568740352", "user_rt": "None"}
{"id": 1029718217730785287, "user_id": 225751736, "username": "noor_bank", "timezone": "+03", "tweet": "This Eid, Noor Bank customers can spoil their loved ones with  http://yougotagift.com\u00a0 eGift cards from their favorite brands!.Enjoy special discounts when you use your Noor Bank debit or credit cards. Offer valid from 14-31 August. Click to know more:  https://yougotagift.com/offers/noorbank/\u00a0\u2026 pic.twitter.com/pk5CWn6SkP", "replies": 0, "retweets": 1, "likes": 3, "date": "2018-08-15", "time": "16:15:29", "hashtags": "", "mentions": "", "location": "", "link": "https://twitter.com/noor_bank/status/1029718217730785287", "user_rt": "None"}
{"id": 1029704103092539392, "user_id": 225751736, "username": "noor_bank", "timezone": "+03", "tweet": "\u0627\u0644\u0645\u064a\u0632\u0627\u062a \u0627\u0644\u0645\u0635\u0631\u0641\u064a\u0629 \u0627\u0644\u0641\u0627\u062e\u0631\u0629 \u0644\u064a\u0633\u062a \u062e\u062f\u0645\u0627\u062a \u0631\u0627\u0642\u064a\u0629 \u0641\u062d\u0633\u0628 \u0628\u0644 \u062a\u0633\u0627\u0639\u062f\u0643 \u0639\u0644\u0649 \u062a\u0648\u0633\u064a\u0639 \u0623\u0641\u0642 \u0623\u0639\u0645\u0627\u0644\u0643.\u0628\u0635\u0641\u062a\u0643 \u0623\u062d\u062f \u0639\u0645\u0644\u0627\u0621 Link Infinite Business\u060c \u064a\u0645\u0643\u0646\u0643 \u0627\u0644\u062d\u0635\u0648\u0644 \u0639\u0644\u0649 \u0645\u0627 \u064a\u0635\u0644 \u0625\u0644\u0649 30 \u0645\u0639\u0627\u0645\u0644\u0629 \u0635\u0631\u0627\u0641 \u0645\u062c\u0627\u0646\u064a\u0629 \u0643\u0644 \u0634\u0647\u0631.\u062d\u0645\u0644 \u0627\u0644\u062a\u0637\u0628\u064a\u0642 \u0627\u0644\u0622\u0646: \u0645\u062a\u062c\u0631 \u062c\u0648\u062c\u0644:  https://goo.gl/xZuxQR\u00a0 \u0645\u062a\u062c\u0631 \u0622\u0628\u0644:  https://goo.gl/jQKqkS\u00a0 pic.twitter.com/Vh7iqDa7Bl", "replies": 0, "retweets": 1, "likes": 2, "date": "2018-08-15", "time": "15:19:23", "hashtags": "", "mentions": "", "location": "", "link": "https://twitter.com/noor_bank/status/1029704103092539392", "user_rt": "None"}
{"id": 1029704004341821441, "user_id": 225751736, "username": "noor_bank", "timezone": "+03", "tweet": "Infinite business banking is not a privilege, it\u2019s a means to help you expand your horizon internationally.  As a Link Infinite Business customer, you can avail up to 30 free teller transactions every monthGoogle Play:  https://goo.gl/xZuxQR\u00a0     Apple:  https://goo.gl/jQKqkS\u00a0 pic.twitter.com/Z5HpZvFVNT", "replies": 0, "retweets": 1, "likes": 2, "date": "2018-08-15", "time": "15:19:00", "hashtags": "", "mentions": "", "location": "", "link": "https://twitter.com/noor_bank/status/1029704004341821441", "user_rt": "None"}
{"id": 1028591048682078209, "user_id": 225751736, "username": "noor_bank", "timezone": "+03", "tweet": "@asooma @EmiratesNBD @FatmaSalim We are sorry to hear this. We\u2019d like to learn more to improve your opinion of Noor Bank .  Please send us a DM with your mobile number.", "replies": 0, "retweets": 0, "likes": 0, "date": "2018-08-12", "time": "13:36:30", "hashtags": "", "mentions": "FatmaSalim,EmiratesNBD,asooma", "location": "", "link": "https://twitter.com/noor_bank/status/1028591048682078209", "user_rt": "None"}
{"id": 1028590786252865536, "user_id": 225751736, "username": "noor_bank", "timezone": "+03", "tweet": "@FatmaSalim @asooma Dear Asma, We are sorry to hear this, our team will be in contact with you shortly to assist you directly.", "replies": 0, "retweets": 0, "likes": 0, "date": "2018-08-12", "time": "13:35:28", "hashtags": "", "mentions": "asooma,FatmaSalim", "location": "", "link": "https://twitter.com/noor_bank/status/1028590786252865536", "user_rt": "None"}
{"id": 1028518603971284992, "user_id": 225751736, "username": "noor_bank", "timezone": "+03", "tweet": "@asooma Dear Asma, please send us a DM with your mobile number and we will arrange to call you back straightaway, or contact us at 800 6667.", "replies": 1, "retweets": 0, "likes": 0, "date": "2018-08-12", "time": "08:48:38", "hashtags": "", "mentions": "asooma", "location": "", "link": "https://twitter.com/noor_bank/status/1028518603971284992", "user_rt": "None"}
{"id": 1027501546286837760, "user_id": 225751736, "username": "noor_bank", "timezone": "+03", "tweet": "@unbegypt @DubaiFirstUAE @HHShkMohd @s3od_1515 \u0646\u0634\u0643\u0631\u0643\u0645 \u0639\u0644\u064a \u062a\u0648\u0627\u0635\u0644\u0643\u0645 \u0645\u0639\u0646\u0627. \u0633\u064a\u0642\u0648\u0645 \u0641\u0631\u064a\u0642 \u0627\u0644\u0639\u0645\u0644 \u0628\u0627\u0644\u062a\u0648\u0627\u0635\u0644 \u0645\u0639\u0643\u0645 \u0645\u0628\u0627\u0634\u0631\u0629", "replies": 0, "retweets": 0, "likes": 0, "date": "2018-08-09", "time": "13:27:13", "hashtags": "", "mentions": "s3od_1515,HHShkMohd,DubaiFirstUAE,unbegypt", "location": "", "link": "https://twitter.com/noor_bank/status/1027501546286837760", "user_rt": "None"}
{"id": 1027494290459713536, "user_id": 225751736, "username": "noor_bank", "timezone": "+03", "tweet": "\u0628\u0643\u0644 \u0641\u062e\u0631 \u0648\u0627\u0639\u062a\u0632\u0627\u0632 \u0646\u0647\u0646\u0626 \u0627\u0644\u0631\u0626\u064a\u0633 \u0627\u0644\u062a\u0646\u0641\u064a\u0630\u064a \u0644\u0646\u0648\u0631 \u0628\u0646\u0643 \u0644\u0627\u062e\u062a\u064a\u0627\u0631\u0647 \u0636\u0645\u0646 \u0642\u0627\u0626\u0645\u0629 \u0627\u0644\u0634\u062e\u0635\u064a\u0627\u062a \u0627\u0644\u062e\u0645\u0633\u064a\u0646 \u0627\u0644\u0648\u0627\u0641\u062f\u0629 \u0627\u0644\u0623\u0643\u062b\u0631 \u062a\u0623\u062b\u064a\u0631\u0627 \u0641\u064a \u062f\u0648\u0644\u0629 \u0627\u0644\u0625\u0645\u0627\u0631\u0627\u062a \u0627\u0644\u0639\u0631\u0628\u064a\u0629 \u0627\u0644\u0645\u062a\u062d\u062f\u0629 \u0645\u0646 \u0642\u0628\u0644 \u0641\u0648\u0631\u0628\u0633 \u0627\u0644\u0634\u0631\u0642 \u0627\u0644\u0623\u0648\u0633\u0637!  https://bit.ly/2M3Z3Yc\u00a0 pic.twitter.com/UeIgf2iv4F", "replies": 0, "retweets": 0, "likes": 6, "date": "2018-08-09", "time": "12:58:23", "hashtags": "", "mentions": "", "location": "", "link": "https://twitter.com/noor_bank/status/1027494290459713536", "user_rt": "None"}
{"id": 1027493776208609280, "user_id": 225751736, "username": "noor_bank", "timezone": "+03", "tweet": "Congratulations to our CEO on being named as one of the 50 most influential expats in the UAE by @ForbesMEEnglish ! Way to go!  https://bit.ly/2M3Z3Yc\u00a0.#NoorBank #UAEBanking #Banking #Dubai #MyDubai #ForbesMiddleEast pic.twitter.com/pKjHEh48ve", "replies": 0, "retweets": 0, "likes": 1, "date": "2018-08-09", "time": "12:56:20", "hashtags": "#NoorBank,#UAEBanking,#Banking,#Dubai,#MyDubai,#ForbesMiddleEast", "mentions": "", "location": "", "link": "https://twitter.com/noor_bank/status/1027493776208609280", "user_rt": "None"}
{"id": 1027188678274236416, "user_id": 225751736, "username": "noor_bank", "timezone": "+03", "tweet": "@iossifidis_john @sanjib_dreamer Dear Sanjib, Thank you for reaching out to Noor, please call our 24-hour contact centre on 800 6667 within the UAE or 009714-4274343 from outside the UAE and our team will assist you.", "replies": 0, "retweets": 0, "likes": 0, "date": "2018-08-08", "time": "16:43:59", "hashtags": "", "mentions": "sanjib_dreamer,iossifidis_john", "location": "", "link": "https://twitter.com/noor_bank/status/1027188678274236416", "user_rt": "None"}
{"id": 1026794304180826114, "user_id": 225751736, "username": "noor_bank", "timezone": "+03", "tweet": "@anuragshuklajee Dear Anurag, we are sorry to hear this and would like to help. Please send us a DM with your mobile number and we will assist you directly.", "replies": 0, "retweets": 0, "likes": 0, "date": "2018-08-07", "time": "14:36:53", "hashtags": "", "mentions": "anuragshuklajee", "location": "", "link": "https://twitter.com/noor_bank/status/1026794304180826114", "user_rt": "None"}
{"id": 1026717687404224513, "user_id": 225751736, "username": "noor_bank", "timezone": "+03", "tweet": "@selvanqoh Dear Selva, our team will be in contact with you shortly to assist you directly.", "replies": 0, "retweets": 0, "likes": 1, "date": "2018-08-07", "time": "09:32:26", "hashtags": "", "mentions": "selvanqoh", "location": "", "link": "https://twitter.com/noor_bank/status/1026717687404224513", "user_rt": "None"}
{"id": 1026455553319624704, "user_id": 225751736, "username": "noor_bank", "timezone": "+03", "tweet": "@selvanqoh Dear Selva, we have tried calling you today but unfortunately there was no response. Please let us know what would be a good time to reach you.", "replies": 1, "retweets": 0, "likes": 1, "date": "2018-08-06", "time": "16:10:49", "hashtags": "", "mentions": "selvanqoh", "location": "", "link": "https://twitter.com/noor_bank/status/1026455553319624704", "user_rt": "None"}
{"id": 1026452204222337024, "user_id": 225751736, "username": "noor_bank", "timezone": "+03", "tweet": "\u0633\u0627\u0647\u0645\u062a \u0627\u0644\u062a\u0643\u0646\u0648\u0644\u0648\u062c\u064a\u0627 \u0641\u064a \u062a\u0648\u0641\u064a\u0631 \u0627\u0644\u0648\u0642\u062a \u0648\u0627\u0644\u062c\u0647\u062f \u0641\u064a \u062d\u064a\u0627\u062a\u0646\u0627 \u0627\u0644\u064a\u0648\u0645\u064a\u0629\u060c \u0641\u0644\u0645\u0627\u0630\u0627 \u0644\u0627 \u0646\u0633\u062e\u0631\u0647\u0627 \u0641\u064a \u062a\u0637\u0648\u0631 \u0627\u0644\u062e\u062f\u0645\u0627\u062a \u0627\u0644\u0645\u0635\u0631\u0641\u064a\u0629\u061f\u062a\u0642\u062f\u0645 \u0627\u0644\u0622\u0646 \u0628\u0637\u0644\u0628 \u0644\u0644\u062d\u0635\u0648\u0644 \u0639\u0644\u0649 \u0628\u0637\u0627\u0642\u0629 \u0627\u0626\u062a\u0645\u0627\u0646 \u0646\u0648\u0631 \u0628\u0646\u0643 \u0623\u0648 \u062a\u0645\u0648\u064a\u0644 \u0634\u062e\u0635\u064a \u0639\u0628\u0631 \u0627\u0644\u0625\u0646\u062a\u0631\u0646\u062a \u0641\u064a \u0623\u0642\u0644 \u0645\u0646 5 \u062f\u0642\u0627\u0626\u0642 \u0648\u0627\u062d\u0635\u0644 \u0639\u0644\u0649 \u0645\u0648\u0627\u0641\u0642\u0629 \u0645\u0633\u0628\u0642\u0629 \u0641\u064a \u063a\u0636\u0648\u0646 30 \u062f\u0642\u064a\u0642\u0629. pic.twitter.com/84l9ZSEoEX", "replies": 0, "retweets": 0, "likes": 3, "date": "2018-08-06", "time": "15:57:30", "hashtags": "", "mentions": "", "location": "", "link": "https://twitter.com/noor_bank/status/1026452204222337024", "user_rt": "None"}
{"id": 1026451954350927872, "user_id": 225751736, "username": "noor_bank", "timezone": "+03", "tweet": "Technology has helped us save time with our everyday tasks. Why not use it in the development of banking services? Now apply for a Noor Bank credit card or Personal Finance online in less than 5 minutes and get a pre-approval in 30 MINUTES. #30MinutesApproval #UAEBanking pic.twitter.com/q9vMAnemED", "replies": 0, "retweets": 0, "likes": 4, "date": "2018-08-06", "time": "15:56:31", "hashtags": "#30MinutesApproval,#UAEBanking", "mentions": "", "location": "", "link": "https://twitter.com/noor_bank/status/1026451954350927872", "user_rt": "None"}
{"id": 1026358555920801793, "user_id": 225751736, "username": "noor_bank", "timezone": "+03", "tweet": "\u0645\u064a\u0632\u0627\u062a \u0645\u0635\u0645\u0645\u0629 \u0644\u062a\u0646\u0645\u064a\u0629 \u0623\u0639\u0645\u0627\u0644\u0643.\u0627\u062d\u0635\u0644 \u0639\u0644\u0649 \u062e\u0635\u0645 50\u066a \u0639\u0644\u0649 \u0631\u0633\u0648\u0645 \u062a\u0623\u0633\u064a\u0633 \u0627\u0644\u062e\u062f\u0645\u0627\u062a \u0627\u0644\u0645\u0635\u0631\u0641\u064a\u0629 \u0639\u0628\u0631 \u0627\u0644\u0625\u0646\u062a\u0631\u0646\u062a \u0644\u0644\u0634\u0631\u0643\u0627\u062a.\u0635\u0645\u0645\u0646\u0627 \u0643\u0644 \u062e\u062f\u0645\u0627\u062a\u0646\u0627 \u0644\u062f\u0639\u0645 \u0646\u0645\u0648 \u0623\u0639\u0645\u0627\u0644\u0643.\u062d\u0645\u0644 \u0627\u0644\u062a\u0637\u0628\u064a\u0642 \u0627\u0644\u0622\u0646:\u0645\u062a\u062c\u0631 \u062c\u0648\u062c\u0644:  https://goo.gl/xZuxQR\u00a0\u0645\u062a\u062c\u0631 \u0622\u0628\u0644:  https://goo.gl/jQKqkS\u00a0 pic.twitter.com/p5zsciUN5E", "replies": 0, "retweets": 0, "likes": 2, "date": "2018-08-06", "time": "09:45:23", "hashtags": "", "mentions": "", "location": "", "link": "https://twitter.com/noor_bank/status/1026358555920801793", "user_rt": "None"}
{"id": 1026358491823386624, "user_id": 225751736, "username": "noor_bank", "timezone": "+03", "tweet": "Link Premium is designed to help you manage and grow your business.Amongst several benefits, also get a 50% discount on corporate online banking set up fees.Download the app nowGoogle Play Store:  https://goo.gl/xZuxQR\u00a0    Apple store:  https://goo.gl/jQKqkS\u00a0 pic.twitter.com/vBWkDRaZPj", "replies": 0, "retweets": 0, "likes": 2, "date": "2018-08-06", "time": "09:45:07", "hashtags": "", "mentions": "", "location": "", "link": "https://twitter.com/noor_bank/status/1026358491823386624", "user_rt": "None"}
{"id": 1026347034356457472, "user_id": 225751736, "username": "noor_bank", "timezone": "+03", "tweet": "@selvanqoh Dear Selva, We are sorry to hear this, our team will be in contact with you shortly to assist you directly.", "replies": 1, "retweets": 0, "likes": 1, "date": "2018-08-06", "time": "08:59:36", "hashtags": "", "mentions": "selvanqoh", "location": "", "link": "https://twitter.com/noor_bank/status/1026347034356457472", "user_rt": "None"}
{"id": 1026075653328830464, "user_id": 225751736, "username": "noor_bank", "timezone": "+03", "tweet": "@selvanqoh Dear Selva, we are sorry to hear this and would like to help. Please send us a DM with your mobile number and we will assist you directly.", "replies": 1, "retweets": 0, "likes": 0, "date": "2018-08-05", "time": "15:01:13", "hashtags": "", "mentions": "selvanqoh", "location": "", "link": "https://twitter.com/noor_bank/status/1026075653328830464", "user_rt": "None"}
{"id": 1025947539860860928, "user_id": 225751736, "username": "noor_bank", "timezone": "+03", "tweet": "@gabrielindubai Dear Gabriel, we are sorry to hear this and would like to help. Please send us a DM with your mobile number and we will assist you directly.", "replies": 0, "retweets": 0, "likes": 0, "date": "2018-08-05", "time": "06:32:09", "hashtags": "", "mentions": "gabrielindubai", "location": "", "link": "https://twitter.com/noor_bank/status/1025947539860860928", "user_rt": "None"}
{"id": 1025946988699734016, "user_id": 225751736, "username": "noor_bank", "timezone": "+03", "tweet": "@iossifidis_john @Mbonoor Dear Abu Noor, thank you so much for sharing this positive feedback with us. You have made our day!", "replies": 0, "retweets": 0, "likes": 0, "date": "2018-08-05", "time": "06:29:57", "hashtags": "", "mentions": "Mbonoor,iossifidis_john", "location": "", "link": "https://twitter.com/noor_bank/status/1025946988699734016", "user_rt": "None"}
{"id": 1024911695117004800, "user_id": 225751736, "username": "noor_bank", "timezone": "+03", "tweet": "\u0627\u0646\u0639\u0634 \u0635\u064a\u0641\u0643 \u0628\u0640 12\u066a \u0645\u0646 \u0627\u0644\u0623\u0631\u0628\u0627\u062d \u0627\u0644\u062a\u0631\u0627\u0643\u0645\u064a\u0629 \u0627\u0644\u0645\u062a\u0648\u0642\u0639\u0629 \u0645\u0639 \u062d\u0633\u0627\u0628 \u0627\u0644\u0648\u062f\u0627\u0626\u0639 \u0627\u0644\u0622\u062c\u0644\u0629.\u062a\u0645\u062a\u0639 \u0628\u0645\u0634\u0627\u0647\u062f\u0629 \u0645\u0639\u062f\u0644 \u0627\u0644\u062a\u0648\u0641\u064a\u0631 \u064a\u0646\u0645\u0648 \u0628\u0646\u0633\u0628\u0629 \u062a\u0635\u0644 \u0625\u0644\u0649 12\u066a \u0644\u0645\u062f\u0629 3 \u0633\u0646\u0648\u0627\u062a \u0645\u0639 \u062d\u0633\u0627\u0628 \u0627\u0644\u0648\u0643\u0627\u0644\u0629 \u0645\u0646 \u0646\u0648\u0631 \u0628\u0646\u0643.\u0644\u0645\u0632\u064a\u062f \u0645\u0646 \u0627\u0644\u0645\u0639\u0644\u0648\u0645\u0627\u062a:  https://goo.gl/xEB7vv\u00a0 \u062a\u0637\u0628\u0642 \u0627\u0644\u0634\u0631\u0648\u0637 \u0648\u0627\u0644\u0623\u062d\u0643\u0627\u0645 pic.twitter.com/zspVwrC7QY", "replies": 0, "retweets": 0, "likes": 2, "date": "2018-08-02", "time": "09:56:04", "hashtags": "", "mentions": "", "location": "", "link": "https://twitter.com/noor_bank/status/1024911695117004800", "user_rt": "None"}
{"id": 1024911598044041216, "user_id": 225751736, "username": "noor_bank", "timezone": "+03", "tweet": "Walk away with a cool 12% anticipated cumulative return with our term deposits.Start a Wakala term deposit with Noor Bank and watch your saving grow at a whopping 12% for a tenor of 3 years.For more:  https://goo.gl/eh5y6b\u00a0Terms and conditions apply pic.twitter.com/27lg0y7SDa", "replies": 0, "retweets": 0, "likes": 3, "date": "2018-08-02", "time": "09:55:41", "hashtags": "", "mentions": "", "location": "", "link": "https://twitter.com/noor_bank/status/1024911598044041216", "user_rt": "None"}
{"id": 1024643209471909888, "user_id": 225751736, "username": "noor_bank", "timezone": "+03", "tweet": "@Amina_Vinka @wsl Dear Mohamed, we are sorry to hear this, our service quality team will be in contact with you shortly to assist you directly.", "replies": 0, "retweets": 0, "likes": 0, "date": "2018-08-01", "time": "16:09:12", "hashtags": "", "mentions": "Amina_Vinka,wsl", "location": "", "link": "https://twitter.com/noor_bank/status/1024643209471909888", "user_rt": "None"}
{"id": 1024225082552590336, "user_id": 225751736, "username": "noor_bank", "timezone": "+03", "tweet": "@sugubush Dear Adigwe, we are sorry to hear this and would like to help. Please send us a DM with your mobile number and we will assist you directly.", "replies": 0, "retweets": 0, "likes": 0, "date": "2018-07-31", "time": "12:27:43", "hashtags": "", "mentions": "sugubush", "location": "", "link": "https://twitter.com/noor_bank/status/1024225082552590336", "user_rt": "None"}
{"id": 1024168665770598401, "user_id": 225751736, "username": "noor_bank", "timezone": "+03", "tweet": "\u0627\u0633\u062a\u0639\u062f \u0644\u0625\u0637\u0644\u0627\u0642 \u0627\u0644\u0639\u0646\u0627\u0646 \u0644\u0645\u0639\u0627\u0645\u0644\u0627\u062a\u0643 \u0627\u0644\u0645\u0635\u0631\u0641\u064a\u0629.\u062a\u0645\u0646\u062d\u0643 \u0628\u0627\u0642\u0629 Link Plus \u062e\u062f\u0645\u0627\u062a \u0645\u0645\u064a\u0632\u0629 \u0643\u0645\u062f\u064a\u0631 \u0639\u0644\u0627\u0642\u0627\u062a \u0645\u062a\u062e\u0635\u0635 \u0644\u062c\u0645\u064a\u0639 \u0627\u062d\u062a\u064a\u0627\u062c\u0627\u062a\u0643 \u0627\u0644\u0645\u0635\u0631\u0641\u064a\u0629 \u0627\u0644\u0630\u064a \u0633\u064a\u0639\u0645\u0644 \u0639\u0644\u0649 \u062a\u0639\u0632\u0632 \u0646\u0634\u0627\u0637\u0643 \u0627\u0644\u062a\u062c\u0627\u0631\u064a\u062d\u0645\u0644 \u0627\u0644\u062a\u0637\u0628\u064a\u0642 \u0627\u0644\u0622\u0646\u0645\u062a\u062c\u0631 \u062c\u0648\u062c\u0644:  https://goo.gl/xZuxQR\u00a0   \u0645\u062a\u062c\u0631 \u0622\u0628\u0644:  https://goo.gl/jQKqkS\u00a0 pic.twitter.com/wQgeB7SvdE", "replies": 1, "retweets": 0, "likes": 1, "date": "2018-07-31", "time": "08:43:32", "hashtags": "", "mentions": "", "location": "", "link": "https://twitter.com/noor_bank/status/1024168665770598401", "user_rt": "None"}
{"id": 1024168618173583361, "user_id": 225751736, "username": "noor_bank", "timezone": "+03", "tweet": "Get ready for a smoother relationship with your bank.Our Link Plus package comes with a dedicated relationship manager for all your banking needs.Download the appGoogle Play Store:  https://goo.gl/xZuxQR\u00a0   Apple store:  https://goo.gl/jQKqkS\u00a0 pic.twitter.com/BNvxv7ZEpN", "replies": 0, "retweets": 0, "likes": 2, "date": "2018-07-31", "time": "08:43:21", "hashtags": "", "mentions": "", "location": "", "link": "https://twitter.com/noor_bank/status/1024168618173583361", "user_rt": "None"}
{"id": 1023907500658229248, "user_id": 225751736, "username": "noor_bank", "timezone": "+03", "tweet": "@ImTheMiracle Dear Customer, we are sorry to hear this and would like to help. Please send us a DM with your mobile number and we will assist you directly.", "replies": 0, "retweets": 0, "likes": 0, "date": "2018-07-30", "time": "15:25:46", "hashtags": "", "mentions": "ImTheMiracle", "location": "", "link": "https://twitter.com/noor_bank/status/1023907500658229248", "user_rt": "None"}
{"id": 1023441915755327488, "user_id": 225751736, "username": "noor_bank", "timezone": "+03", "tweet": "@ca_amitt Thank you for your feedback, which helps us to keep improving!  We have forwarded your suggestion to the concerned department.", "replies": 0, "retweets": 0, "likes": 1, "date": "2018-07-29", "time": "08:35:42", "hashtags": "", "mentions": "ca_amitt", "location": "", "link": "https://twitter.com/noor_bank/status/1023441915755327488", "user_rt": "None"}
{"id": 1023441400896126976, "user_id": 225751736, "username": "noor_bank", "timezone": "+03", "tweet": "@zayed_alhajeri Thank you so much for sharing this positive feedback with us. You have made our day!", "replies": 0, "retweets": 0, "likes": 0, "date": "2018-07-29", "time": "08:33:39", "hashtags": "", "mentions": "zayed_alhajeri", "location": "", "link": "https://twitter.com/noor_bank/status/1023441400896126976", "user_rt": "None"}
{"id": 1022420067206811648, "user_id": 225751736, "username": "noor_bank", "timezone": "+03", "tweet": "\u0644\u062f\u064a\u0643 \u0637\u0645\u0648\u062d\u060c \u0644\u062f\u064a\u0646\u0627 \u0627\u0644\u062e\u0628\u0631\u0629!\u0631\u0643\u0632 \u0639\u0644\u0649 \u0641\u0631\u0635\u0643 \u0627\u0644\u0645\u0633\u062a\u0642\u0628\u0644\u064a\u0629 \u0645\u0639 \u0634\u0631\u064a\u0643\u0643 \u0627\u0644\u0645\u0635\u0631\u0641\u064a \u0645\u0646 \u062e\u0644\u0627\u0644 \u062a\u0637\u0628\u064a\u0642 \u0646\u0648\u0631 \u0627\u0644\u062a\u062c\u0627\u0631\u0629 \u0644\u062a\u0633\u0631\u064a\u0639 \u0627\u0644\u0623\u0639\u0645\u0627\u0644 \u0645\u0646 \u0646\u0648\u0631 \u0628\u0646\u0643 \u0627\u0644\u0645\u0635\u0645\u0645 \u0644\u062a\u0633\u0647\u064a\u0644 \u0643\u0644 \u062c\u0627\u0646\u0628 \u0645\u0646 \u062c\u0648\u0627\u0646\u0628 \u0623\u0639\u0645\u0627\u0644\u0643 \u0627\u0644\u062a\u062c\u0627\u0631\u064a\u0629.\u062d\u0645\u0644 \u0627\u0644\u062a\u0637\u0628\u064a\u0642 \u0627\u0644\u0622\u0646\u0645\u062a\u062c\u0631 \u062c\u0648\u062c\u0644:  https://goo.gl/xZuxQR\u00a0 \u0645\u062a\u062c\u0631 \u0622\u0628\u0644:  https://goo.gl/jQKqkS\u00a0 pic.twitter.com/e7NtCRqAMm", "replies": 0, "retweets": 0, "likes": 2, "date": "2018-07-26", "time": "12:55:14", "hashtags": "", "mentions": "", "location": "", "link": "https://twitter.com/noor_bank/status/1022420067206811648", "user_rt": "None"}
{"id": 1022419984394473472, "user_id": 225751736, "username": "noor_bank", "timezone": "+03", "tweet": "You have ambition, we have expertise!Noor Trade Biz Accelerator helps you focus on your aspirations with a platform designed to simplify every aspect of your business journey.Google Play Store:  https://goo.gl/xZuxQR\u00a0 Apple store:  https://goo.gl/jQKqkS\u00a0 pic.twitter.com/GJz2APoNCV", "replies": 2, "retweets": 0, "likes": 2, "date": "2018-07-26", "time": "12:54:54", "hashtags": "", "mentions": "", "location": "", "link": "https://twitter.com/noor_bank/status/1022419984394473472", "user_rt": "None"}
{"id": 1021355640663552000, "user_id": 225751736, "username": "noor_bank", "timezone": "+03", "tweet": "\u0645\u0641\u0636\u0644 \u0643\u0627\u062c\u064a\u062c\u064a\u060c \u0631\u0626\u064a\u0633 \u0642\u0633\u0645 \u0627\u0644\u062e\u062f\u0645\u0627\u062a \u0627\u0644\u0645\u0635\u0631\u0641\u064a\u0629 \u0644\u0644\u0623\u0641\u0631\u0627\u062f\u060c \u064a\u062a\u062d\u062f\u062b \u0625\u0644\u0649 \u0635\u062d\u064a\u0641\u0629 \u062c\u0644\u0641 \u0646\u064a\u0648\u0632 \u0639\u0646 \u0627\u0644\u0625\u0633\u062a\u0631\u0627\u062a\u064a\u062c\u064a\u0629 \u0627\u0644\u062c\u062f\u064a\u062f\u0629 \u0644\u0644\u062e\u062f\u0645\u0627\u062a \u0627\u0644\u0645\u0635\u0631\u0641\u064a\u0629 \u0644\u0644\u0623\u0641\u0631\u0627\u062f \u0627\u0644\u062a\u064a \u0627\u0639\u062a\u0645\u062f\u0647\u0627 \u0627\u0644\u0628\u0646\u0643 \u0648\u062a\u0645\u0627\u0634\u064a\u0647\u0627 \u0645\u0639 \u0627\u0644\u062a\u0632\u0627\u0645 \u0627\u0644\u0628\u0646\u0643 \u0628\u062a\u0642\u062f\u064a\u0645 \u062e\u062f\u0645\u0627\u062a \u0645\u062a\u0645\u064a\u0632\u0629 \u0644\u0644\u0639\u0645\u0644\u0627\u0621.\u0644\u0642\u0631\u0627\u0621\u0629 \u0627\u0644\u0645\u0632\u064a\u062f:  https://goo.gl/59LQtU\u00a0 pic.twitter.com/Nicb1xfuWy", "replies": 0, "retweets": 0, "likes": 2, "date": "2018-07-23", "time": "14:25:35", "hashtags": "", "mentions": "", "location": "", "link": "https://twitter.com/noor_bank/status/1021355640663552000", "user_rt": "None"}
{"id": 1021355306738225152, "user_id": 225751736, "username": "noor_bank", "timezone": "+03", "tweet": "An interview with Mufazzal Kajiji, Head of Retail Banking, Noor Bank for Gulf News. He talks about the new retail banking strategy adopted by the bank and how it is in line with our commitment to deliver outstanding customer experiences. To read more:  https://goo.gl/59LQtU\u00a0 pic.twitter.com/Z90XZBc9w2", "replies": 0, "retweets": 0, "likes": 3, "date": "2018-07-23", "time": "14:24:15", "hashtags": "", "mentions": "", "location": "", "link": "https://twitter.com/noor_bank/status/1021355306738225152", "user_rt": "None"}
{"id": 1019945920845238272, "user_id": 225751736, "username": "noor_bank", "timezone": "+03", "tweet": "\u0627\u0646\u0639\u0634 \u0635\u064a\u0641\u0643 \u0628\u0640 12\u066a \u0645\u0646 \u0627\u0644\u0623\u0631\u0628\u0627\u062d \u0627\u0644\u062a\u0631\u0627\u0643\u0645\u064a\u0629 \u0627\u0644\u0645\u062a\u0648\u0642\u0639\u0629 \u0645\u0639 \u062d\u0633\u0627\u0628 \u0627\u0644\u0648\u062f\u0627\u0626\u0639 \u0627\u0644\u0622\u062c\u0644\u0629.\u062a\u0645\u062a\u0639 \u0628\u0645\u0634\u0627\u0647\u062f\u0629 \u0645\u0639\u062f\u0644 \u0627\u0644\u062a\u0648\u0641\u064a\u0631 \u064a\u0646\u0645\u0648 \u0628\u0646\u0633\u0628\u0629 \u062a\u0635\u0644 \u0625\u0644\u0649 12\u066a \u0644\u0645\u062f\u0629 3 \u0633\u0646\u0648\u0627\u062a. \u0645\u0639 \u062d\u0633\u0627\u0628 \u0627\u0644\u0648\u0643\u0627\u0644\u0629 \u0645\u0646 \u0646\u0648\u0631 \u0628\u0646\u0643.\u0644\u0644\u0627\u0634\u062a\u0631\u0627\u0643 \u0623\u0631\u0633\u0644 \"SAVE\" \u0625\u0644\u0649 3526\u0644\u0645\u0632\u064a\u062f \u0645\u0646 \u0627\u0644\u0645\u0639\u0644\u0648\u0645\u0627\u062a:  https://goo.gl/xEB7vv\u00a0\u062a\u0637\u0628\u0642 \u0627\u0644\u0634\u0631\u0648\u0637 pic.twitter.com/F97OLiPO2R", "replies": 0, "retweets": 0, "likes": 1, "date": "2018-07-19", "time": "17:03:51", "hashtags": "", "mentions": "", "location": "", "link": "https://twitter.com/noor_bank/status/1019945920845238272", "user_rt": "None"}
{"id": 1019945796781953027, "user_id": 225751736, "username": "noor_bank", "timezone": "+03", "tweet": "Walk away with a cool 12% anticipated cumulative return with our term deposits.Start a Wakala term deposit with Noor Bank and watch your saving grow at a whopping 12% for a tenor of 3 years.SMS \u2018SAVE\u2019 to 3526For more:  https://goo.gl/eh5y6b\u00a0T&C apply pic.twitter.com/vDG3zJVyvC", "replies": 0, "retweets": 0, "likes": 1, "date": "2018-07-19", "time": "17:03:22", "hashtags": "", "mentions": "", "location": "", "link": "https://twitter.com/noor_bank/status/1019945796781953027", "user_rt": "None"}
{"id": 1017378685064753152, "user_id": 225751736, "username": "noor_bank", "timezone": "+03", "tweet": "Our CEO John Iossifidis has been featured on the cover of Islamic Business & Finance Magazine. In the article, John explains the strategy of the bank and speaks of the various initiatives we have launched to support our vision, mission and purpose.  https://goo.gl/sCNrRC\u00a0 pic.twitter.com/gZXmA1Xiro", "replies": 0, "retweets": 0, "likes": 7, "date": "2018-07-12", "time": "15:02:35", "hashtags": "", "mentions": "", "location": "", "link": "https://twitter.com/noor_bank/status/1017378685064753152", "user_rt": "None"}
{"id": 1016549150949822464, "user_id": 225751736, "username": "noor_bank", "timezone": "+03", "tweet": "@syeraheelhashmi Dear Raheel, thank you for reaching out to Noor. How can we help you today?", "replies": 0, "retweets": 0, "likes": 0, "date": "2018-07-10", "time": "08:06:18", "hashtags": "", "mentions": "syeraheelhashmi", "location": "", "link": "https://twitter.com/noor_bank/status/1016549150949822464", "user_rt": "None"}
{"id": 1016309500163297280, "user_id": 225751736, "username": "noor_bank", "timezone": "+03", "tweet": "Dear Zineb, we are sorry to hear this and would like to help. Please send us a DM with your mobile number and we will assist you directly", "replies": 1, "retweets": 0, "likes": 1, "date": "2018-07-09", "time": "16:14:01", "hashtags": "", "mentions": "", "location": "", "link": "https://twitter.com/noor_bank/status/1016309500163297280", "user_rt": "None"}
{"id": 1015830835273129984, "user_id": 225751736, "username": "noor_bank", "timezone": "+03", "tweet": "@auctionscarl Dear Carl, We are sorry to hear this, we have forwarded your feedback to our concerned team and they will revert back to you shortly.", "replies": 0, "retweets": 0, "likes": 0, "date": "2018-07-08", "time": "08:31:59", "hashtags": "", "mentions": "auctionscarl", "location": "", "link": "https://twitter.com/noor_bank/status/1015830835273129984", "user_rt": "None"}
{"id": 1014023677741068290, "user_id": 225751736, "username": "noor_bank", "timezone": "+03", "tweet": "@AbbyBalabagan Dear Abby, we are sorry to hear this and would like to help. Please send us a DM with your mobile number and we will assist you directly.", "replies": 0, "retweets": 0, "likes": 0, "date": "2018-07-03", "time": "08:50:59", "hashtags": "", "mentions": "AbbyBalabagan", "location": "", "link": "https://twitter.com/noor_bank/status/1014023677741068290", "user_rt": "None"}
