{"id": 1033502658697412613, "user_id": 816999733050765316, "username": "translationcom5", "timezone": "+03", "tweet": "Things that you probably did not know about the Spanish Language http://translationcompanyindubai.com/things-that-you-probably-did-not-know-about-the-spanish-language/\u00a0\u2026#spanish #spanish_language #translation_company_in_dubai pic.twitter.com/f60d7h9bcn", "replies": 0, "retweets": 0, "likes": 0, "date": "2018-08-26", "time": "02:53:30", "hashtags": "#spanish,#spanish_language,#translation_company_in_dubai", "mentions": "", "location": "", "link": "https://twitter.com/translationcom5/status/1033502658697412613", "user_rt": "None"}
