{"id": 1024010527599734785, "user_id": 30643836, "username": "marcuscent", "timezone": "+03", "tweet": "@BoycottTerra happy to support you. The most corrupt organisation I've ever had to deal with.", "replies": 0, "retweets": 0, "likes": 0, "date": "2018-07-30", "time": "22:15:09", "hashtags": "", "mentions": "BoycottTerra", "location": "", "link": "https://twitter.com/marcuscent/status/1024010527599734785", "user_rt": "None"}
{"id": 1021316438978695168, "user_id": 30643836, "username": "marcuscent", "timezone": "+03", "tweet": "@SixtUK Can you telll me where to find the phone number for the branch in Nimes Airport?", "replies": 1, "retweets": 0, "likes": 0, "date": "2018-07-23", "time": "11:49:48", "hashtags": "", "mentions": "SixtUK", "location": "", "link": "https://twitter.com/marcuscent/status/1021316438978695168", "user_rt": "None"}
